{
    "annotations": {
        "list": [
            {
                "builtIn": 1,
                "datasource": "-- Grafana --",
                "enable": true,
                "hide": true,
                "iconColor": "rgba(0, 211, 255, 1)",
                "name": "Annotations & Alerts",
                "type": "dashboard"
            }
        ]
    },
    "editable": true,
    "gnetId": null,
    "graphTooltip": 1,
    "id": null,
    "links": [],
    "panels": [
        {
            "datasource": "Prometheus",
            "gridPos": {
                "h": 1,
                "w": 24,
                "x": 0,
                "y": 0
            },
            "id": 100,
            "title": "DNS SHIELD - SYSTÈME DE DÉTECTION MALVEILLANTE",
            "type": "row"
        },
        {
            "datasource": "Prometheus",
            "fieldConfig": {
                "defaults": {
                    "color": {
                        "mode": "thresholds"
                    },
                    "mappings": [],
                    "thresholds": {
                        "mode": "absolute",
                        "steps": [
                            {
                                "color": "green",
                                "value": null
                            }
                        ]
                    },
                    "unit": "short"
                }
            },
            "gridPos": {
                "h": 8,
                "w": 4,
                "x": 0,
                "y": 1
            },
            "id": 2,
            "options": {
                "colorMode": "value",
                "graphMode": "area",
                "justifyMode": "auto",
                "orientation": "auto",
                "reduceOptions": {
                    "calcs": [
                        "lastNotNull"
                    ],
                    "fields": "",
                    "values": false
                },
                "text": {},
                "textMode": "auto"
            },
            "pluginVersion": "9.0.0",
            "targets": [
                {
                    "expr": "sum(dns_queries_total)",
                    "refId": "A"
                }
            ],
            "title": "Total Requêtes DNS",
            "type": "stat"
        },
        {
            "datasource": "Prometheus",
            "fieldConfig": {
                "defaults": {
                    "color": {
                        "mode": "thresholds"
                    },
                    "mappings": [],
                    "thresholds": {
                        "mode": "absolute",
                        "steps": [
                            {
                                "color": "red",
                                "value": null
                            },
                            {
                                "color": "orange",
                                "value": 50
                            },
                            {
                                "color": "green",
                                "value": 80
                            }
                        ]
                    },
                    "unit": "percent"
                }
            },
            "gridPos": {
                "h": 8,
                "w": 4,
                "x": 4,
                "y": 1
            },
            "id": 3,
            "options": {
                "colorMode": "value",
                "graphMode": "area",
                "justifyMode": "auto",
                "orientation": "auto",
                "reduceOptions": {
                    "calcs": [
                        "lastNotNull"
                    ],
                    "fields": "",
                    "values": false
                },
                "text": {},
                "textMode": "auto"
            },
            "pluginVersion": "9.0.0",
            "targets": [
                {
                    "expr": "(sum(dns_blocks_total) / sum(dns_queries_total)) * 100",
                    "refId": "A"
                }
            ],
            "title": "Taux de Blocage",
            "type": "stat"
        },
        {
            "datasource": "Prometheus",
            "fieldConfig": {
                "defaults": {
                    "color": {
                        "mode": "thresholds"
                    },
                    "mappings": [],
                    "thresholds": {
                        "mode": "absolute",
                        "steps": [
                            {
                                "color": "green",
                                "value": null
                            },
                            {
                                "color": "yellow",
                                "value": 1000
                            },
                            {
                                "color": "red",
                                "value": 5000
                            }
                        ]
                    },
                    "unit": "ms"
                }
            },
            "gridPos": {
                "h": 8,
                "w": 4,
                "x": 8,
                "y": 1
            },
            "id": 4,
            "options": {
                "colorMode": "value",
                "graphMode": "area",
                "justifyMode": "auto",
                "orientation": "auto",
                "reduceOptions": {
                    "calcs": [
                        "mean"
                    ],
                    "fields": "",
                    "values": false
                },
                "text": {},
                "textMode": "auto"
            },
            "pluginVersion": "9.0.0",
            "targets": [
                {
                    "expr": "(rate(http_request_duration_seconds_sum{endpoint=\"/analyze\"}[5m]) / rate(http_request_duration_seconds_count{endpoint=\"/analyze\"}[5m])) * 1000",
                    "refId": "A"
                }
            ],
            "title": "Latence Moyenne",
            "type": "stat"
        },
        {
            "datasource": "Prometheus",
            "fieldConfig": {
                "defaults": {
                    "color": {
                        "mode": "thresholds"
                    },
                    "mappings": [],
                    "thresholds": {
                        "mode": "absolute",
                        "steps": [
                            {
                                "color": "green",
                                "value": null
                            },
                            {
                                "color": "red",
                                "value": 1
                            }
                        ]
                    },
                    "unit": "short"
                }
            },
            "gridPos": {
                "h": 8,
                "w": 4,
                "x": 12,
                "y": 1
            },
            "id": 5,
            "options": {
                "colorMode": "value",
                "graphMode": "area",
                "justifyMode": "auto",
                "orientation": "auto",
                "reduceOptions": {
                    "calcs": [
                        "lastNotNull"
                    ],
                    "fields": "",
                    "values": false
                },
                "text": {},
                "textMode": "auto"
            },
            "pluginVersion": "9.0.0",
            "targets": [
                {
                    "expr": "sum(dns_errors_total)",
                    "refId": "A"
                }
            ],
            "title": "Erreurs Totales",
            "type": "stat"
        },
        {
            "datasource": "Prometheus",
            "fieldConfig": {
                "defaults": {
                    "color": {
                        "mode": "thresholds"
                    },
                    "mappings": [],
                    "thresholds": {
                        "mode": "absolute",
                        "steps": [
                            {
                                "color": "green",
                                "value": null
                            }
                        ]
                    },
                    "unit": "short"
                }
            },
            "gridPos": {
                "h": 8,
                "w": 4,
                "x": 16,
                "y": 1
            },
            "id": 6,
            "options": {
                "colorMode": "value",
                "graphMode": "area",
                "justifyMode": "auto",
                "orientation": "auto",
                "reduceOptions": {
                    "calcs": [
                        "lastNotNull"
                    ],
                    "fields": "",
                    "values": false
                },
                "text": {},
                "textMode": "auto"
            },
            "pluginVersion": "9.0.0",
            "targets": [
                {
                    "expr": "sum(dns_blocks_total)",
                    "refId": "A"
                }
            ],
            "title": "Domaines Bloqués",
            "type": "stat"
        },
        {
            "datasource": "Prometheus",
            "fieldConfig": {
                "defaults": {
                    "color": {
                        "mode": "thresholds"
                    },
                    "mappings": [],
                    "thresholds": {
                        "mode": "absolute",
                        "steps": [
                            {
                                "color": "blue",
                                "value": null
                            }
                        ]
                    },
                    "unit": "short"
                }
            },
            "gridPos": {
                "h": 8,
                "w": 4,
                "x": 20,
                "y": 1
            },
            "id": 7,
            "options": {
                "colorMode": "value",
                "graphMode": "area",
                "justifyMode": "auto",
                "orientation": "auto",
                "reduceOptions": {
                    "calcs": [
                        "lastNotNull"
                    ],
                    "fields": "",
                    "values": false
                },
                "text": {},
                "textMode": "auto"
            },
            "pluginVersion": "9.0.0",
            "targets": [
                {
                    "expr": "sum(dns_accepts_total)",
                    "refId": "A"
                }
            ],
            "title": "Domaines Acceptés",
            "type": "stat"
        },
        {
            "datasource": "Prometheus",
            "gridPos": {
                "h": 1,
                "w": 24,
                "x": 0,
                "y": 9
            },
            "id": 101,
            "title": "ACTIVITÉ DNS EN TEMPS RÉEL",
            "type": "row"
        },
        {
            "datasource": "Prometheus",
            "fieldConfig": {
                "defaults": {
                    "color": {
                        "mode": "palette-classic"
                    },
                    "custom": {
                        "axisLabel": "",
                        "axisPlacement": "auto",
                        "barAlignment": 0,
                        "drawStyle": "line",
                        "fillOpacity": 20,
                        "gradientMode": "none",
                        "hideFrom": {
                            "tooltip": false,
                            "viz": false,
                            "legend": false
                        },
                        "lineInterpolation": "smooth",
                        "lineWidth": 2,
                        "pointSize": 5,
                        "scaleDistribution": {
                            "type": "linear"
                        },
                        "showPoints": "never",
                        "spanNulls": false,
                        "stacking": {
                            "group": "A",
                            "mode": "none"
                        },
                        "thresholdsStyle": {
                            "mode": "off"
                        }
                    },
                    "mappings": [],
                    "thresholds": {
                        "mode": "absolute",
                        "steps": [
                            {
                                "color": "green",
                                "value": null
                            }
                        ]
                    },
                    "unit": "reqps"
                }
            },
            "gridPos": {
                "h": 10,
                "w": 12,
                "x": 0,
                "y": 10
            },
            "id": 8,
            "options": {
                "legend": {
                    "calcs": [
                        "mean",
                        "max"
                    ],
                    "displayMode": "table",
                    "placement": "bottom"
                },
                "tooltip": {
                    "mode": "multi"
                }
            },
            "targets": [
                {
                    "expr": "rate(dns_queries_total{service=\"gateway\"}[1m])",
                    "legendFormat": "Requêtes/sec",
                    "refId": "A"
                }
            ],
            "title": "Requêtes DNS par Seconde",
            "type": "timeseries"
        },
        {
            "datasource": "Prometheus",
            "fieldConfig": {
                "defaults": {
                    "color": {
                        "mode": "palette-classic"
                    },
                    "custom": {
                        "axisLabel": "",
                        "axisPlacement": "auto",
                        "barAlignment": 0,
                        "drawStyle": "line",
                        "fillOpacity": 30,
                        "gradientMode": "opacity",
                        "hideFrom": {
                            "tooltip": false,
                            "viz": false,
                            "legend": false
                        },
                        "lineInterpolation": "smooth",
                        "lineWidth": 2,
                        "pointSize": 5,
                        "scaleDistribution": {
                            "type": "linear"
                        },
                        "showPoints": "never",
                        "spanNulls": false,
                        "stacking": {
                            "group": "A",
                            "mode": "normal"
                        },
                        "thresholdsStyle": {
                            "mode": "off"
                        }
                    },
                    "mappings": [],
                    "thresholds": {
                        "mode": "absolute",
                        "steps": [
                            {
                                "color": "green",
                                "value": null
                            }
                        ]
                    },
                    "unit": "short"
                }
            },
            "gridPos": {
                "h": 10,
                "w": 12,
                "x": 12,
                "y": 10
            },
            "id": 9,
            "options": {
                "legend": {
                    "calcs": [
                        "sum",
                        "mean"
                    ],
                    "displayMode": "table",
                    "placement": "bottom"
                },
                "tooltip": {
                    "mode": "multi"
                }
            },
            "targets": [
                {
                    "expr": "rate(dns_blocks_total[1m])",
                    "legendFormat": "Bloqués - {{reason}}",
                    "refId": "A"
                },
                {
                    "expr": "rate(dns_accepts_total[1m])",
                    "legendFormat": "Acceptés",
                    "refId": "B"
                }
            ],
            "title": "Blocages vs Acceptations (Rate)",
            "type": "timeseries"
        },
        {
            "datasource": "Prometheus",
            "gridPos": {
                "h": 1,
                "w": 24,
                "x": 0,
                "y": 20
            },
            "id": 102,
            "title": "PERFORMANCES DES SERVICES",
            "type": "row"
        },
        {
            "datasource": "Prometheus",
            "fieldConfig": {
                "defaults": {
                    "color": {
                        "mode": "palette-classic"
                    },
                    "custom": {
                        "axisLabel": "",
                        "axisPlacement": "auto",
                        "barAlignment": 0,
                        "drawStyle": "line",
                        "fillOpacity": 10,
                        "gradientMode": "none",
                        "hideFrom": {
                            "tooltip": false,
                            "viz": false,
                            "legend": false
                        },
                        "lineInterpolation": "smooth",
                        "lineWidth": 2,
                        "pointSize": 5,
                        "scaleDistribution": {
                            "type": "linear"
                        },
                        "showPoints": "auto",
                        "spanNulls": false,
                        "stacking": {
                            "group": "A",
                            "mode": "none"
                        },
                        "thresholdsStyle": {
                            "mode": "off"
                        }
                    },
                    "mappings": [],
                    "thresholds": {
                        "mode": "absolute",
                        "steps": [
                            {
                                "color": "green",
                                "value": null
                            },
                            {
                                "color": "yellow",
                                "value": 1000
                            },
                            {
                                "color": "red",
                                "value": 3000
                            }
                        ]
                    },
                    "unit": "ms"
                }
            },
            "gridPos": {
                "h": 10,
                "w": 16,
                "x": 0,
                "y": 21
            },
            "id": 10,
            "options": {
                "legend": {
                    "calcs": [
                        "mean",
                        "max",
                        "min"
                    ],
                    "displayMode": "table",
                    "placement": "bottom"
                },
                "tooltip": {
                    "mode": "multi"
                }
            },
            "targets": [
                {
                    "expr": "(rate(dns_processing_duration_seconds_sum{stage=\"1\"}[1m]) / rate(dns_processing_duration_seconds_count{stage=\"1\"}[1m])) * 1000",
                    "legendFormat": "Stage 1 - DGA Detector",
                    "refId": "A"
                },
                {
                    "expr": "(rate(dns_processing_duration_seconds_sum{stage=\"2\"}[1m]) / rate(dns_processing_duration_seconds_count{stage=\"2\"}[1m])) * 1000",
                    "legendFormat": "Stage 2 - BERT Service",
                    "refId": "B"
                },
                {
                    "expr": "(rate(dns_processing_duration_seconds_sum{stage=\"3\"}[1m]) / rate(dns_processing_duration_seconds_count{stage=\"3\"}[1m])) * 1000",
                    "legendFormat": "Stage 3 - Ensemble ML",
                    "refId": "C"
                }
            ],
            "title": "Latence par Service (Cascade)",
            "type": "timeseries"
        },
        {
            "datasource": "Prometheus",
            "fieldConfig": {
                "defaults": {
                    "color": {
                        "mode": "thresholds"
                    },
                    "mappings": [],
                    "max": 5000,
                    "min": 0,
                    "thresholds": {
                        "mode": "absolute",
                        "steps": [
                            {
                                "color": "green",
                                "value": null
                            },
                            {
                                "color": "yellow",
                                "value": 1000
                            },
                            {
                                "color": "orange",
                                "value": 2000
                            },
                            {
                                "color": "red",
                                "value": 3000
                            }
                        ]
                    },
                    "unit": "ms"
                }
            },
            "gridPos": {
                "h": 10,
                "w": 8,
                "x": 16,
                "y": 21
            },
            "id": 11,
            "options": {
                "orientation": "auto",
                "reduceOptions": {
                    "calcs": [
                        "lastNotNull"
                    ],
                    "fields": "",
                    "values": false
                },
                "showThresholdLabels": false,
                "showThresholdMarkers": true,
                "text": {}
            },
            "pluginVersion": "9.0.0",
            "targets": [
                {
                    "expr": "(rate(dns_processing_duration_seconds_sum{stage=\"1\"}[5m]) / rate(dns_processing_duration_seconds_count{stage=\"1\"}[5m])) * 1000",
                    "refId": "A"
                }
            ],
            "title": "DGA Latency",
            "type": "gauge"
        },
        {
            "datasource": "Prometheus",
            "fieldConfig": {
                "defaults": {
                    "color": {
                        "mode": "thresholds"
                    },
                    "mappings": [],
                    "max": 5000,
                    "min": 0,
                    "thresholds": {
                        "mode": "absolute",
                        "steps": [
                            {
                                "color": "green",
                                "value": null
                            },
                            {
                                "color": "yellow",
                                "value": 1000
                            },
                            {
                                "color": "orange",
                                "value": 2000
                            },
                            {
                                "color": "red",
                                "value": 3000
                            }
                        ]
                    },
                    "unit": "ms"
                }
            },
            "gridPos": {
                "h": 5,
                "w": 8,
                "x": 16,
                "y": 31
            },
            "id": 12,
            "options": {
                "orientation": "auto",
                "reduceOptions": {
                    "calcs": [
                        "lastNotNull"
                    ],
                    "fields": "",
                    "values": false
                },
                "showThresholdLabels": false,
                "showThresholdMarkers": true,
                "text": {}
            },
            "pluginVersion": "9.0.0",
            "targets": [
                {
                    "expr": "(rate(dns_processing_duration_seconds_sum{stage=\"2\"}[5m]) / rate(dns_processing_duration_seconds_count{stage=\"2\"}[5m])) * 1000",
                    "refId": "A"
                }
            ],
            "title": "BERT Latency",
            "type": "gauge"
        },
        {
            "datasource": "Prometheus",
            "fieldConfig": {
                "defaults": {
                    "color": {
                        "mode": "thresholds"
                    },
                    "mappings": [],
                    "max": 5000,
                    "min": 0,
                    "thresholds": {
                        "mode": "absolute",
                        "steps": [
                            {
                                "color": "green",
                                "value": null
                            },
                            {
                                "color": "yellow",
                                "value": 1000
                            },
                            {
                                "color": "orange",
                                "value": 2000
                            },
                            {
                                "color": "red",
                                "value": 3000
                            }
                        ]
                    },
                    "unit": "ms"
                }
            },
            "gridPos": {
                "h": 5,
                "w": 8,
                "x": 16,
                "y": 36
            },
            "id": 13,
            "options": {
                "orientation": "auto",
                "reduceOptions": {
                    "calcs": [
                        "lastNotNull"
                    ],
                    "fields": "",
                    "values": false
                },
                "showThresholdLabels": false,
                "showThresholdMarkers": true,
                "text": {}
            },
            "pluginVersion": "9.0.0",
            "targets": [
                {
                    "expr": "(rate(dns_processing_duration_seconds_sum{stage=\"3\"}[5m]) / rate(dns_processing_duration_seconds_count{stage=\"3\"}[5m])) * 1000",
                    "refId": "A"
                }
            ],
            "title": "Ensemble Latency",
            "type": "gauge"
        },
        {
            "datasource": "Prometheus",
            "gridPos": {
                "h": 1,
                "w": 24,
                "x": 0,
                "y": 41
            },
            "id": 103,
            "title": "DISTRIBUTION DES SCORES ML",
            "type": "row"
        },
        {
            "datasource": "Prometheus",
            "fieldConfig": {
                "defaults": {
                    "color": {
                        "mode": "palette-classic"
                    },
                    "custom": {
                        "axisLabel": "",
                        "axisPlacement": "auto",
                        "barAlignment": 0,
                        "drawStyle": "bars",
                        "fillOpacity": 80,
                        "gradientMode": "hue",
                        "hideFrom": {
                            "tooltip": false,
                            "viz": false,
                            "legend": false
                        },
                        "lineInterpolation": "linear",
                        "lineWidth": 1,
                        "pointSize": 5,
                        "scaleDistribution": {
                            "type": "linear"
                        },
                        "showPoints": "auto",
                        "spanNulls": false,
                        "stacking": {
                            "group": "A",
                            "mode": "none"
                        },
                        "thresholdsStyle": {
                            "mode": "off"
                        }
                    },
                    "mappings": [],
                    "thresholds": {
                        "mode": "absolute",
                        "steps": [
                            {
                                "color": "green",
                                "value": null
                            }
                        ]
                    },
                    "unit": "short"
                }
            },
            "gridPos": {
                "h": 10,
                "w": 12,
                "x": 0,
                "y": 42
            },
            "id": 14,
            "options": {
                "legend": {
                    "calcs": [],
                    "displayMode": "list",
                    "placement": "bottom"
                },
                "tooltip": {
                    "mode": "single"
                }
            },
            "targets": [
                {
                    "expr": "sum by (le) (rate(dga_score_distribution_bucket[5m]))",
                    "legendFormat": "Score {{le}}",
                    "refId": "A"
                }
            ],
            "title": "Distribution Scores DGA",
            "type": "timeseries"
        },
        {
            "datasource": "Prometheus",
            "fieldConfig": {
                "defaults": {
                    "color": {
                        "mode": "palette-classic"
                    },
                    "custom": {
                        "axisLabel": "",
                        "axisPlacement": "auto",
                        "barAlignment": 0,
                        "drawStyle": "bars",
                        "fillOpacity": 80,
                        "gradientMode": "hue",
                        "hideFrom": {
                            "tooltip": false,
                            "viz": false,
                            "legend": false
                        },
                        "lineInterpolation": "linear",
                        "lineWidth": 1,
                        "pointSize": 5,
                        "scaleDistribution": {
                            "type": "linear"
                        },
                        "showPoints": "auto",
                        "spanNulls": false,
                        "stacking": {
                            "group": "A",
                            "mode": "none"
                        },
                        "thresholdsStyle": {
                            "mode": "off"
                        }
                    },
                    "mappings": [],
                    "thresholds": {
                        "mode": "absolute",
                        "steps": [
                            {
                                "color": "green",
                                "value": null
                            }
                        ]
                    },
                    "unit": "short"
                }
            },
            "gridPos": {
                "h": 10,
                "w": 12,
                "x": 12,
                "y": 42
            },
            "id": 15,
            "options": {
                "legend": {
                    "calcs": [],
                    "displayMode": "list",
                    "placement": "bottom"
                },
                "tooltip": {
                    "mode": "single"
                }
            },
            "targets": [
                {
                    "expr": "sum by (le) (rate(bert_score_distribution_bucket[5m]))",
                    "legendFormat": "Score {{le}}",
                    "refId": "A"
                }
            ],
            "title": "Distribution Scores BERT",
            "type": "timeseries"
        },
        {
            "datasource": "Prometheus",
            "gridPos": {
                "h": 1,
                "w": 24,
                "x": 0,
                "y": 52
            },
            "id": 104,
            "title": "CACHE & SYSTÈME",
            "type": "row"
        },
        {
            "datasource": "Prometheus",
            "fieldConfig": {
                "defaults": {
                    "color": {
                        "mode": "palette-classic"
                    },
                    "custom": {
                        "axisLabel": "",
                        "axisPlacement": "auto",
                        "barAlignment": 0,
                        "drawStyle": "line",
                        "fillOpacity": 20,
                        "gradientMode": "none",
                        "hideFrom": {
                            "tooltip": false,
                            "viz": false,
                            "legend": false
                        },
                        "lineInterpolation": "smooth",
                        "lineWidth": 2,
                        "pointSize": 5,
                        "scaleDistribution": {
                            "type": "linear"
                        },
                        "showPoints": "never",
                        "spanNulls": false,
                        "stacking": {
                            "group": "A",
                            "mode": "normal"
                        },
                        "thresholdsStyle": {
                            "mode": "off"
                        }
                    },
                    "mappings": [],
                    "thresholds": {
                        "mode": "absolute",
                        "steps": [
                            {
                                "color": "green",
                                "value": null
                            }
                        ]
                    },
                    "unit": "ops"
                }
            },
            "gridPos": {
                "h": 8,
                "w": 12,
                "x": 0,
                "y": 53
            },
            "id": 16,
            "options": {
                "legend": {
                    "calcs": [
                        "sum"
                    ],
                    "displayMode": "table",
                    "placement": "bottom"
                },
                "tooltip": {
                    "mode": "multi"
                }
            },
            "targets": [
                {
                    "expr": "rate(cache_hits_total[1m])",
                    "legendFormat": "Cache Hits",
                    "refId": "A"
                },
                {
                    "expr": "rate(cache_misses_total[1m])",
                    "legendFormat": "Cache Misses",
                    "refId": "B"
                }
            ],
            "title": "Cache Performance (Redis)",
            "type": "timeseries"
        },
        {
            "datasource": "Prometheus",
            "fieldConfig": {
                "defaults": {
                    "color": {
                        "mode": "thresholds"
                    },
                    "mappings": [],
                    "max": 100,
                    "min": 0,
                    "thresholds": {
                        "mode": "absolute",
                        "steps": [
                            {
                                "color": "red",
                                "value": null
                            },
                            {
                                "color": "yellow",
                                "value": 50
                            },
                            {
                                "color": "green",
                                "value": 80
                            }
                        ]
                    },
                    "unit": "percent"
                }
            },
            "gridPos": {
                "h": 8,
                "w": 6,
                "x": 12,
                "y": 53
            },
            "id": 17,
            "options": {
                "orientation": "auto",
                "reduceOptions": {
                    "calcs": [
                        "lastNotNull"
                    ],
                    "fields": "",
                    "values": false
                },
                "showThresholdLabels": false,
                "showThresholdMarkers": true,
                "text": {}
            },
            "pluginVersion": "9.0.0",
            "targets": [
                {
                    "expr": "cache_hit_ratio * 100",
                    "refId": "A"
                }
            ],
            "title": "Cache Hit Ratio",
            "type": "gauge"
        },
        {
            "datasource": "Prometheus",
            "fieldConfig": {
                "defaults": {
                    "color": {
                        "mode": "thresholds"
                    },
                    "mappings": [],
                    "thresholds": {
                        "mode": "absolute",
                        "steps": [
                            {
                                "color": "green",
                                "value": null
                            },
                            {
                                "color": "yellow",
                                "value": 1000000
                            },
                            {
                                "color": "red",
                                "value": 10000000
                            }
                        ]
                    },
                    "unit": "bytes"
                }
            },
            "gridPos": {
                "h": 8,
                "w": 6,
                "x": 18,
                "y": 53
            },
            "id": 18,
            "options": {
                "colorMode": "value",
                "graphMode": "area",
                "justifyMode": "auto",
                "orientation": "auto",
                "reduceOptions": {
                    "calcs": [
                        "lastNotNull"
                    ],
                    "fields": "",
                    "values": false
                },
                "text": {},
                "textMode": "auto"
            },
            "pluginVersion": "9.0.0",
            "targets": [
                {
                    "expr": "cache_size_bytes",
                    "refId": "A"
                }
            ],
            "title": "Cache Size",
            "type": "stat"
        },
        {
            "datasource": "Prometheus",
            "gridPos": {
                "h": 1,
                "w": 24,
                "x": 0,
                "y": 61
            },
            "id": 105,
            "title": "DÉTAILS PAR SERVICE",
            "type": "row"
        },
        {
            "datasource": "Prometheus",
            "fieldConfig": {
                "defaults": {
                    "color": {
                        "mode": "palette-classic"
                    },
                    "custom": {
                        "axisLabel": "",
                        "axisPlacement": "auto",
                        "barAlignment": 0,
                        "drawStyle": "line",
                        "fillOpacity": 0,
                        "gradientMode": "none",
                        "hideFrom": {
                            "tooltip": false,
                            "viz": false,
                            "legend": false
                        },
                        "lineInterpolation": "linear",
                        "lineWidth": 1,
                        "pointSize": 5,
                        "scaleDistribution": {
                            "type": "linear"
                        },
                        "showPoints": "auto",
                        "spanNulls": false,
                        "stacking": {
                            "group": "A",
                            "mode": "none"
                        },
                        "thresholdsStyle": {
                            "mode": "off"
                        }
                    },
                    "mappings": [],
                    "thresholds": {
                        "mode": "absolute",
                        "steps": [
                            {
                                "color": "green",
                                "value": null
                            }
                        ]
                    }
                }
            },
            "gridPos": {
                "h": 10,
                "w": 24,
                "x": 0,
                "y": 62
            },
            "id": 19,
            "options": {
                "legend": {
                    "calcs": [
                        "lastNotNull",
                        "sum"
                    ],
                    "displayMode": "table",
                    "placement": "right"
                },
                "tooltip": {
                    "mode": "multi"
                }
            },
            "targets": [
                {
                    "expr": "dns_queries_total",
                    "legendFormat": "{{service}} - Requêtes",
                    "refId": "A"
                }
            ],
            "title": "Requêtes par Service",
            "type": "timeseries"
        },
        {
            "datasource": "Prometheus",
            "fieldConfig": {
                "defaults": {
                    "color": {
                        "mode": "thresholds"
                    },
                    "custom": {
                        "align": "auto",
                        "displayMode": "auto"
                    },
                    "mappings": [],
                    "thresholds": {
                        "mode": "absolute",
                        "steps": [
                            {
                                "color": "green",
                                "value": null
                            }
                        ]
                    }
                }
            },
            "gridPos": {
                "h": 8,
                "w": 12,
                "x": 0,
                "y": 72
            },
            "id": 20,
            "options": {
                "showHeader": true,
                "sortBy": [
                    {
                        "desc": true,
                        "displayName": "Value"
                    }
                ]
            },
            "pluginVersion": "9.0.0",
            "targets": [
                {
                    "expr": "topk(10, dns_blocks_total)",
                    "format": "table",
                    "instant": true,
                    "refId": "A"
                }
            ],
            "title": "Top Blocages par Raison",
            "transformations": [
                {
                    "id": "organize",
                    "options": {
                        "excludeByName": {
                            "Time": true,
                            "__name__": true,
                            "instance": true,
                            "job": true
                        },
                        "indexByName": {},
                        "renameByName": {
                            "Value": "Nombre",
                            "reason": "Raison",
                            "service": "Service"
                        }
                    }
                }
            ],
            "type": "table"
        },
        {
            "datasource": "Prometheus",
            "fieldConfig": {
                "defaults": {
                    "color": {
                        "mode": "palette-classic"
                    },
                    "custom": {
                        "hideFrom": {
                            "tooltip": false,
                            "viz": false,
                            "legend": false
                        }
                    },
                    "mappings": []
                }
            },
            "gridPos": {
                "h": 8,
                "w": 12,
                "x": 12,
                "y": 72
            },
            "id": 21,
            "options": {
                "displayLabels": [
                    "percent"
                ],
                "legend": {
                    "displayMode": "table",
                    "placement": "right",
                    "values": [
                        "value",
                        "percent"
                    ]
                },
                "pieType": "donut",
                "reduceOptions": {
                    "calcs": [
                        "lastNotNull"
                    ],
                    "fields": "",
                    "values": false
                },
                "tooltip": {
                    "mode": "single"
                }
            },
            "targets": [
                {
                    "expr": "dns_blocks_total",
                    "legendFormat": "{{reason}}",
                    "refId": "A"
                }
            ],
            "title": "Répartition des Blocages",
            "type": "piechart"
        }
    ],
    "refresh": "10s",
    "schemaVersion": 36,
    "style": "dark",
    "tags": [
        "dns",
        "security",
        "ml",
        "dga"
    ],
    "templating": {
        "list": []
    },
    "time": {
        "from": "now-1h",
        "to": "now"
    },
    "timepicker": {},
    "timezone": "",
    "title": "DNS Shield - Monitoring",
    "uid": "dns-shield-pro",
    "version": 1
}